scriptter.py
scriptter-0.3.dist-info/DESCRIPTION.rst
scriptter-0.3.dist-info/entry_points.txt
scriptter-0.3.dist-info/METADATA
scriptter-0.3.dist-info/metadata.json
scriptter-0.3.dist-info/RECORD
scriptter-0.3.dist-info/top_level.txt
scriptter-0.3.dist-info/WHEEL
