Metadata-Version: 2.0
Name: scriptter
Version: 0.3
Summary: cron's missing brain. Stateful, time-based scripting.
Home-page: https://github.com/eykd/scriptter
Author: David Eyk
Author-email: deyk@crossway.org
License: MIT
Keywords: social media twitter scheduling cron
Platform: UNKNOWN
Classifier: Development Status :: 3 - Alpha
Classifier: Intended Audience :: Developers
Classifier: Topic :: Software Development :: Build Tools
Classifier: Topic :: Office/Business :: Scheduling
Classifier: License :: OSI Approved :: MIT License
Classifier: Programming Language :: Python :: 2
Classifier: Programming Language :: Python :: 2.6
Classifier: Programming Language :: Python :: 2.7
Classifier: Programming Language :: Python :: 3
Classifier: Programming Language :: Python :: 3.2
Classifier: Programming Language :: Python :: 3.3
Classifier: Programming Language :: Python :: 3.4
Requires-Dist: six (==1.9.0)
Requires-Dist: docopt (==0.6.2)
Requires-Dist: parsedatetime (==1.4)
Requires-Dist: path.py (==7.3)
Requires-Dist: pytz (==2015.2)
Requires-Dist: PyYAML (==3.11)
Provides-Extra: dev
Requires-Dist: check-manifest; extra == 'dev'
Provides-Extra: test
Requires-Dist: coverage; extra == 'test'
Requires-Dist: coveralls; extra == 'test'
Requires-Dist: ensure; extra == 'test'
Requires-Dist: green; extra == 'test'
Requires-Dist: mock; extra == 'test'
Requires-Dist: pep8; extra == 'test'
Requires-Dist: tox; extra == 'test'
